pyuule/__init__.py
pyuule/encoding.py
pyuule/types.py
pyuule-0.1.0.dist-info/METADATA
pyuule-0.1.0.dist-info/WHEEL
pyuule-0.1.0.dist-info/RECORD
