Metadata-Version: 2.1
Name: pyuule
Version: 0.1.0
Summary: A library for decoding and encoding UULEs
License: MIT
Author: Ryan Pepper
Author-email: ryan.pepper1@gmail.com
Requires-Python: >=3.10,<4.0
Classifier: License :: OSI Approved :: MIT License
Classifier: Programming Language :: Python :: 3
Classifier: Programming Language :: Python :: 3.10
Classifier: Programming Language :: Python :: 3.11
